{
	"cmake" : 
	{
		"generator" : 
		{
			"multiConfig" : false,
			"name" : "Ninja"
		},
		"paths" : 
		{
			"cmake" : "C:/msys64/mingw64/bin/cmake.exe",
			"cpack" : "C:/msys64/mingw64/bin/cpack.exe",
			"ctest" : "C:/msys64/mingw64/bin/ctest.exe",
			"root" : "C:/msys64/mingw64/share/cmake"
		},
		"version" : 
		{
			"isDirty" : false,
			"major" : 4,
			"minor" : 3,
			"patch" : 3,
			"string" : "4.3.3",
			"suffix" : ""
		}
	},
	"objects" : 
	[
		{
			"jsonFile" : "codemodel-v2-618d5275fada913bc864.json",
			"kind" : "codemodel",
			"version" : 
			{
				"major" : 2,
				"minor" : 10
			}
		},
		{
			"jsonFile" : "cache-v2-21b0aa7012f68b4f80ff.json",
			"kind" : "cache",
			"version" : 
			{
				"major" : 2,
				"minor" : 0
			}
		},
		{
			"jsonFile" : "cmakeFiles-v1-4320e3140b1d3bd76519.json",
			"kind" : "cmakeFiles",
			"version" : 
			{
				"major" : 1,
				"minor" : 1
			}
		}
	],
	"reply" : 
	{
		"cache-v2" : 
		{
			"jsonFile" : "cache-v2-21b0aa7012f68b4f80ff.json",
			"kind" : "cache",
			"version" : 
			{
				"major" : 2,
				"minor" : 0
			}
		},
		"cmakeFiles-v1" : 
		{
			"jsonFile" : "cmakeFiles-v1-4320e3140b1d3bd76519.json",
			"kind" : "cmakeFiles",
			"version" : 
			{
				"major" : 1,
				"minor" : 1
			}
		},
		"codemodel-v2" : 
		{
			"jsonFile" : "codemodel-v2-618d5275fada913bc864.json",
			"kind" : "codemodel",
			"version" : 
			{
				"major" : 2,
				"minor" : 10
			}
		}
	}
}
